quickpath/__init__.py
quickpath/_version.py
quickpath/getpath.py
quickpath-0.9.3.dist-info/LICENSE
quickpath-0.9.3.dist-info/METADATA
quickpath-0.9.3.dist-info/WHEEL
quickpath-0.9.3.dist-info/top_level.txt
quickpath-0.9.3.dist-info/RECORD
