Metadata-Version: 2.1
Name: quickpath
Version: 0.9.3
Summary: Easy access to elements of collection/object structures
Home-page: https://github.com/axonmatics/quickpath
Author: Axonmatics Ltd.
Author-email: info@axonmatics.com
License: UNKNOWN
Project-URL: Bug Tracker, https://github.com/axonmatics/quickpath/issues
Platform: UNKNOWN
Classifier: Programming Language :: Python :: 3
Classifier: License :: OSI Approved :: MIT License
Classifier: Operating System :: OS Independent
Requires-Python: >=3.6
License-File: LICENSE
